snookerbot
