Metadata-Version: 2.1
Name: python-snookerbot
Version: 1.3.0
Summary: Snookerbot
Home-page: https://github.com/alexander-schillemans/python-snookerbot
Download-URL: https://github.com/alexander-schillemans/python-snookerbot/archive/refs/tags/1.3.0.tar.gz
Author: Alexander Schillemans
Author-email: alexander.schillemans@hotmail.com
License: GPL-3.0-or-later
Keywords: snooker,snooker.org,bot,snookerbot,api
Classifier: Development Status :: 3 - Alpha
Classifier: Intended Audience :: Developers
Classifier: Topic :: Software Development :: Build Tools
Classifier: License :: OSI Approved :: GNU General Public License v3 or later (GPLv3+)
Classifier: Programming Language :: Python :: 3.10
License-File: LICENSE.txt
